dt_templates/__init__.py
dt_templates/chainsaw.py
dt_templates/forest_owner.py
dt_templates/forwarder.py
dt_templates/forwarding_agency.py
dt_templates/harvester.py
dt_templates/json_models.py
dt_templates/laboratory.py
dt_templates/log_loading_unit.py
dt_templates/log_truck_scale.py
dt_templates/mill_gate.py
dt_templates/production_team.py
dt_templates/truck.py
dt_templates/wood_yard.py
dt_templates/template_json/__init__.py
ml/__init__.py
ml/app_logger.py
ml/callback.py
ml/ditto_feature.py
ml/dt_factory.py
ml/entry.py
ml/feature.py
ml/identifier.py
ml/parameters.py
ml/role.py
ml/s3i_connector.py
ml/thing.py
ml/tools.py
ml/fml40/__init__.py
ml/fml40/features/__init__.py
ml/fml40/features/functionalities/__init__.py
ml/fml40/features/functionalities/accepts_felling_jobs.py
ml/fml40/features/functionalities/accepts_felling_support_jobs.py
ml/fml40/features/functionalities/accepts_forwarding_jobs.py
ml/fml40/features/functionalities/accepts_log_loading_unit.py
ml/fml40/features/functionalities/accepts_log_loading_unit_in_wood_yard.py
ml/fml40/features/functionalities/accepts_log_measurements.py
ml/fml40/features/functionalities/accepts_log_transportaition_jobs.py
ml/fml40/features/functionalities/accepts_log_truck_weight_measurement.py
ml/fml40/features/functionalities/accepts_moisture_measurement.py
ml/fml40/features/functionalities/accepts_move_commands.py
ml/fml40/features/functionalities/accepts_passability_report.py
ml/fml40/features/functionalities/accepts_proximity_alert.py
ml/fml40/features/functionalities/accepts_shield_commands.py
ml/fml40/features/functionalities/accepts_single_tree_felling_jobs.py
ml/fml40/features/functionalities/accepts_winch_command.py
ml/fml40/features/functionalities/calculates_machine_operation_cost.py
ml/fml40/features/functionalities/classifies_tree_species.py
ml/fml40/features/functionalities/controls_forest_production.py
ml/fml40/features/functionalities/controls_sawmill_production.py
fml40_reference_implementation-1.0.0.dist-info/LICENSE.txt
fml40_reference_implementation-1.0.0.dist-info/METADATA
fml40_reference_implementation-1.0.0.dist-info/WHEEL
fml40_reference_implementation-1.0.0.dist-info/top_level.txt
fml40_reference_implementation-1.0.0.dist-info/RECORD
