Metadata-Version: 2.1
Name: fml40-reference-implementation
Version: 1.0.0
Summary: fml40 reference implementation basic functions
Home-page: https://www.kwh40.de/
Author: Kompetenzzentrum Wald und Holz 4.0
Author-email: s3i@kwh40.de
Classifier: Programming Language :: Python :: 3
Classifier: License :: OSI Approved :: GNU Library or Lesser General Public License (LGPL)
Classifier: Operating System :: OS Independent
License-File: LICENSE.txt
Requires-Dist: requests
Requires-Dist: jsonschema
Requires-Dist: s3i
